fds/__init__.py
fds/sdk/__init__.py
fds/sdk/QuantitativeResearchEnvironment/__init__.py
fds/sdk/QuantitativeResearchEnvironment/api_client.py
fds/sdk/QuantitativeResearchEnvironment/configuration.py
fds/sdk/QuantitativeResearchEnvironment/exceptions.py
fds/sdk/QuantitativeResearchEnvironment/model_utils.py
fds/sdk/QuantitativeResearchEnvironment/rest.py
fds/sdk/QuantitativeResearchEnvironment/api/__init__.py
fds/sdk/QuantitativeResearchEnvironment/api/calculations_api.py
fds/sdk/QuantitativeResearchEnvironment/api/files_api.py
fds/sdk/QuantitativeResearchEnvironment/apis/__init__.py
fds/sdk/QuantitativeResearchEnvironment/model/__init__.py
fds/sdk/QuantitativeResearchEnvironment/model/calculation.py
fds/sdk/QuantitativeResearchEnvironment/model/calculation_status.py
fds/sdk/QuantitativeResearchEnvironment/model/file_upload_status.py
fds/sdk/QuantitativeResearchEnvironment/models/__init__.py
fds.sdk.QuantitativeResearchEnvironment-0.21.6.dist-info/LICENSE
fds.sdk.QuantitativeResearchEnvironment-0.21.6.dist-info/METADATA
fds.sdk.QuantitativeResearchEnvironment-0.21.6.dist-info/WHEEL
fds.sdk.QuantitativeResearchEnvironment-0.21.6.dist-info/top_level.txt
fds.sdk.QuantitativeResearchEnvironment-0.21.6.dist-info/RECORD
